MANIFEST.in
README.rst
setup.py
Flask_arrest.egg-info/PKG-INFO
Flask_arrest.egg-info/SOURCES.txt
Flask_arrest.egg-info/dependency_links.txt
Flask_arrest.egg-info/not-zip-safe
Flask_arrest.egg-info/requires.txt
Flask_arrest.egg-info/top_level.txt
flask_arrest/__init__.py
flask_arrest/helpers.py
flask_arrest/renderers.py
flask_arrest/resources.py
flask_arrest/templates/exception.html