Metadata-Version: 1.1
Name: Flask-arrest
Version: 0.5.0
Summary: A small Flask extension to ease the creation of REST apis.
Home-page: http://github.com/mbr/Flask-arrest
Author: Marc Brinkmann
Author-email: git@marcbrinkmann.de
License: MIT
Platform: UNKNOWN
Classifier: Programming Language :: Python :: 2
Classifier: Programming Language :: Python :: 3
